Metadata-Version: 2.1
Name: mt5se
Version: 0.2.39
Summary: mt5se provides access to Stock Exchanges to python programs through Metatrader and some brokers. It can be used with NYSE,Nasdaq, B3(Brazilian Stock Exchange)
Home-page: https://github.com/paulo-al-castro/mt5se/
Author: Paulo Andre Lima de Castro
Author-email: paulo.al.castro@gmail.com
License: MIT
Classifier: Programming Language :: Python :: 3
Classifier: License :: OSI Approved :: MIT License
Classifier: Operating System :: OS Independent
License-File: LICENSE.txt
